basematic/__init__.py
basematic/cmd.py
basematic/setting.py
basematic/bio/__init__.py
basematic/bio/bam/__init__.py
basematic/bio/bam/read.py
basematic/bio/bam/stats.py
basematic/bio/bed/__init__.py
basematic/bio/cnv/__init__.py
basematic/bio/cnv/align.py
basematic/bio/cnv/bin_count.py
basematic/bio/cnv/cbs.py
basematic/bio/cnv/normalize.py
basematic/bio/dropseq/__init__.py
basematic/bio/fastq/Files.py
basematic/bio/fastq/Stats.py
basematic/bio/fastq/__init__.py
basematic/bio/resource/__init__.py
basematic/bio/resource/gene_infos.py
basematic/bio/resource/gene_rifs.py
basematic/bio/rnaseq/DESeq2.py
basematic/bio/rnaseq/__init__.py
basematic/bio/rnaseq/barcode.py
basematic/bio/rnaseq/barcode_stats.py
basematic/bio/rnaseq/reads_tagging.py
basematic/bio/snv/__init__.py
basematic/bio/snv/_cmd.py
basematic/bio/snv/annovar.py
basematic/bio/snv/gatk.py
basematic/bio/snv/pipe.py
basematic/bio/snv/quality.py
basematic/bio/snv/vcf.py
basematic/exec/__init__.py
basematic/exec/bash.py
basematic/file/DataBase.py
basematic/file/Folder.py
basematic/file/Read.py
basematic/file/__init__.py
basematic/mgt/__init__.py
basematic/mgt/_cmd.py
basematic/mgt/check.py
basematic/mgt/command.py
basematic/mgt/config.py
basematic/mgt/jobs.py
basematic/mgt/resource.py
basematic/server/SimpleHttp.py
basematic/server/__init__.py
basematic/src/__init__.py
basematic/utils/__init__.py
basematic/utils/clean.py
basematic-0.1.2.dist-info/DESCRIPTION.rst
basematic-0.1.2.dist-info/METADATA
basematic-0.1.2.dist-info/RECORD
basematic-0.1.2.dist-info/WHEEL
basematic-0.1.2.dist-info/entry_points.txt
basematic-0.1.2.dist-info/metadata.json
basematic-0.1.2.dist-info/top_level.txt
